tados_stopwatch/__init__.py
tados_stopwatch-0.0.2.dist-info/METADATA
tados_stopwatch-0.0.2.dist-info/WHEEL
tados_stopwatch-0.0.2.dist-info/top_level.txt
tados_stopwatch-0.0.2.dist-info/RECORD
