Metadata-Version: 2.4
Name: tados-stopwatch
Version: 0.0.2
Summary: Easily measure time
Author-email: NumbersTada <tadaktatak61@gmail.com>
Classifier: Programming Language :: Python :: 3
Classifier: Operating System :: OS Independent
Classifier: License :: OSI Approved :: MIT License
Requires-Python: >=3.6
